Metadata-Version: 2.1
Name: django-to-sqlserver-description
Version: 0.1.7
Summary: 根据django 的 model 自动生成sqlserver的列说明
Home-page: https://www.cnblogs.com/Evan-fanfan/
Author: evanyang
Author-email: lightyiyi@qq.com
License: MIT tencent_message
Platform: UNKNOWN
